README.rst
setup.py
python_upsource_api.egg-info/PKG-INFO
python_upsource_api.egg-info/SOURCES.txt
python_upsource_api.egg-info/dependency_links.txt
python_upsource_api.egg-info/requires.txt
python_upsource_api.egg-info/top_level.txt
upsource/HubClient.py
upsource/UpsourceClient.py
upsource/__init__.py
upsource/exception.py