Metadata-Version: 1.1
Name: python-upsource-api
Version: 1.0.0
Summary: Jetbrains Upsource API handler for Python
Home-page: https://github.com/shijl0925/python-upsource-api
Author: Jialiang Shi
Author-email: kevin09254930sjl@gmail.com
License: MIT
Keywords: api upsource hub
Platform: UNKNOWN
Classifier: Development Status :: 5 - Production/Stable
Classifier: Environment :: Plugins
Classifier: Intended Audience :: Developers
Classifier: License :: OSI Approved :: MIT License
Classifier: Operating System :: OS Independent
Classifier: Programming Language :: Python :: 2.7
Classifier: Programming Language :: Python :: 3.3
Classifier: Programming Language :: Python :: 3.4
Classifier: Programming Language :: Python :: 3.5
Classifier: Programming Language :: Python :: 3.6
Classifier: Programming Language :: Python :: 3.7
Classifier: Topic :: Software Development
